{"id":"e7213987-f7d2-425a-b382-f342f4f7306e","map":"AmbroseValley","date":"2026-02-11","duration_s":364,"players":[{"id":"bc24cc0b-eb28-4af3-8ce8-cec15510f245","bot":false,"path":[[0,104,897],[20,111,891],[25,133,890],[30,154,888],[35,174,878],[40,187,868],[45,195,849],[50,202,845],[55,199,844],[60,197,847],[65,195,841],[70,197,846],[75,200,849],[81,210,845],[86,220,838],[91,231,861],[101,228,837],[106,242,826],[111,247,790],[116,258,768],[121,271,750],[126,291,731],[131,306,703],[136,322,706],[141,338,691],[146,336,664],[151,342,665],[156,337,640],[161,334,605],[166,316,594],[171,306,581],[181,311,571],[186,308,565],[191,302,567],[196,303,549],[201,306,533],[206,305,533],[211,301,535],[221,292,528],[231,289,538],[246,292,530],[257,279,529],[262,272,510],[267,268,506],[272,263,514],[277,267,515],[282,281,501],[287,317,493],[292,345,496],[297,340,476],[302,327,460],[307,312,451],[312,314,445],[317,308,435],[327,314,434],[332,326,428],[337,329,420],[342,343,391],[347,336,394],[352,336,395],[362,333,393]],"events":[{"t":36,"e":"Loot","c":"loot","x":174,"y":876},{"t":48,"e":"Loot","c":"loot","x":196,"y":839},{"t":64,"e":"BotKill","c":"kill","x":195,"y":841},{"t":67,"e":"Loot","c":"loot","x":196,"y":845},{"t":67,"e":"Loot","c":"loot","x":196,"y":845},{"t":78,"e":"Loot","c":"loot","x":203,"y":849},{"t":93,"e":"Loot","c":"loot","x":231,"y":861},{"t":132,"e":"Loot","c":"loot","x":307,"y":701},{"t":147,"e":"Loot","c":"loot","x":336,"y":665},{"t":148,"e":"Loot","c":"loot","x":336,"y":665},{"t":174,"e":"BotKill","c":"kill","x":307,"y":582},{"t":184,"e":"Loot","c":"loot","x":312,"y":565},{"t":185,"e":"Loot","c":"loot","x":312,"y":565},{"t":203,"e":"Loot","c":"loot","x":308,"y":531},{"t":213,"e":"Loot","c":"loot","x":296,"y":538},{"t":223,"e":"Loot","c":"loot","x":292,"y":528},{"t":226,"e":"Loot","c":"loot","x":294,"y":527},{"t":241,"e":"BotKill","c":"kill","x":289,"y":538},{"t":248,"e":"Loot","c":"loot","x":293,"y":527},{"t":249,"e":"Loot","c":"loot","x":293,"y":527},{"t":263,"e":"Loot","c":"loot","x":272,"y":504},{"t":264,"e":"Loot","c":"loot","x":272,"y":504},{"t":270,"e":"Loot","c":"loot","x":263,"y":514},{"t":309,"e":"Loot","c":"loot","x":317,"y":445},{"t":324,"e":"BotKill","c":"kill","x":313,"y":433},{"t":331,"e":"Loot","c":"loot","x":326,"y":428},{"t":332,"e":"Loot","c":"loot","x":326,"y":428},{"t":353,"e":"BotKill","c":"kill","x":336,"y":395},{"t":364,"e":"BotKilled","c":"death","x":332,"y":394}]}]}