{"id":"f06f75c0-a2ef-42ed-9fba-a836b201ec87","map":"AmbroseValley","date":"2026-02-10","duration_s":347,"players":[{"id":"d0a4f572-c8f3-4bcb-acf7-0af1ad19b635","bot":false,"path":[[0,688,243],[20,666,254],[25,638,252],[30,643,256],[35,627,256],[40,599,263],[45,593,299],[50,602,322],[60,609,343],[65,601,359],[70,589,379],[75,588,395],[80,591,401],[85,583,408],[115,587,406],[120,591,411],[125,581,416],[130,601,404],[136,609,401],[141,616,396],[146,625,400],[151,612,396],[156,619,406],[166,626,398],[171,634,389],[181,639,409],[186,623,423],[191,620,447],[196,643,473],[201,665,497],[206,640,510],[211,622,538],[216,609,565],[221,606,558],[246,596,556],[251,607,560],[256,600,577],[261,604,566],[266,599,565],[271,594,574],[291,591,576],[311,576,565],[317,562,559],[322,539,561],[327,531,559],[332,526,545],[337,522,526],[342,539,509],[347,542,507]],"events":[{"t":26,"e":"Loot","c":"loot","x":638,"y":252},{"t":26,"e":"Loot","c":"loot","x":638,"y":252},{"t":54,"e":"Loot","c":"loot","x":602,"y":323},{"t":54,"e":"Loot","c":"loot","x":602,"y":323},{"t":54,"e":"Loot","c":"loot","x":602,"y":323},{"t":70,"e":"BotKill","c":"kill","x":589,"y":379},{"t":77,"e":"Loot","c":"loot","x":590,"y":397},{"t":80,"e":"Loot","c":"loot","x":591,"y":401},{"t":82,"e":"Loot","c":"loot","x":590,"y":404},{"t":82,"e":"Loot","c":"loot","x":590,"y":404},{"t":125,"e":"Loot","c":"loot","x":581,"y":416},{"t":146,"e":"Loot","c":"loot","x":625,"y":400},{"t":149,"e":"Loot","c":"loot","x":615,"y":397},{"t":154,"e":"Loot","c":"loot","x":619,"y":403},{"t":158,"e":"Loot","c":"loot","x":621,"y":407},{"t":176,"e":"Loot","c":"loot","x":637,"y":385},{"t":218,"e":"Loot","c":"loot","x":609,"y":565},{"t":223,"e":"Loot","c":"loot","x":604,"y":557},{"t":241,"e":"Loot","c":"loot","x":605,"y":557},{"t":260,"e":"Loot","c":"loot","x":606,"y":565},{"t":288,"e":"Loot","c":"loot","x":594,"y":574},{"t":305,"e":"Loot","c":"loot","x":589,"y":576}]}]}